odoo/addons/base_tier_validation_waiting/README.rst
odoo/addons/base_tier_validation_waiting/__init__.py
odoo/addons/base_tier_validation_waiting/__manifest__.py
odoo/addons/base_tier_validation_waiting/i18n/base_tier_validation_waiting.pot
odoo/addons/base_tier_validation_waiting/i18n/es.po
odoo/addons/base_tier_validation_waiting/i18n/it.po
odoo/addons/base_tier_validation_waiting/i18n/tr.po
odoo/addons/base_tier_validation_waiting/models/__init__.py
odoo/addons/base_tier_validation_waiting/models/tier_definition.py
odoo/addons/base_tier_validation_waiting/models/tier_review.py
odoo/addons/base_tier_validation_waiting/models/tier_validation.py
odoo/addons/base_tier_validation_waiting/readme/CONFIGURE.rst
odoo/addons/base_tier_validation_waiting/readme/CONTRIBUTORS.rst
odoo/addons/base_tier_validation_waiting/readme/DESCRIPTION.rst
odoo/addons/base_tier_validation_waiting/readme/DEVELOP.rst
odoo/addons/base_tier_validation_waiting/readme/ROADMAP.rst
odoo/addons/base_tier_validation_waiting/readme/USAGE.rst
odoo/addons/base_tier_validation_waiting/security/ir.model.access.csv
odoo/addons/base_tier_validation_waiting/static/description/icon.png
odoo/addons/base_tier_validation_waiting/static/description/index.html
odoo/addons/base_tier_validation_waiting/static/src/xml/tier_review_template.xml
odoo/addons/base_tier_validation_waiting/tests/__init__.py
odoo/addons/base_tier_validation_waiting/tests/test_tier_validation.py
odoo/addons/base_tier_validation_waiting/views/tier_definition_views.xml
odoo_addon_base_tier_validation_waiting-16.0.1.0.1.2.dist-info/METADATA
odoo_addon_base_tier_validation_waiting-16.0.1.0.1.2.dist-info/WHEEL
odoo_addon_base_tier_validation_waiting-16.0.1.0.1.2.dist-info/top_level.txt
odoo_addon_base_tier_validation_waiting-16.0.1.0.1.2.dist-info/RECORD
